DDMongoLogger/__init__.py
DDMongoLogger/mongodb_logger.py
DDMongoLogger-0.1.4.dist-info/LICENSE
DDMongoLogger-0.1.4.dist-info/METADATA
DDMongoLogger-0.1.4.dist-info/WHEEL
DDMongoLogger-0.1.4.dist-info/top_level.txt
DDMongoLogger-0.1.4.dist-info/RECORD
