Metadata-Version: 2.1
Name: DDMongoLogger
Version: 0.1.4
Summary: simple mongoDb logger
Home-page: 
Author: Alex Pavlov
Author-email: apavlov@datadimensions.com
License: MIT
License-File: LICENSE
Requires-Dist: pymongo
